odoo/addons/stock_picking_reallocation/README.rst
odoo/addons/stock_picking_reallocation/__init__.py
odoo/addons/stock_picking_reallocation/__manifest__.py
odoo/addons/stock_picking_reallocation/i18n/it.po
odoo/addons/stock_picking_reallocation/i18n/sk.po
odoo/addons/stock_picking_reallocation/i18n/stock_picking_reallocation.pot
odoo/addons/stock_picking_reallocation/models/__init__.py
odoo/addons/stock_picking_reallocation/models/stock_picking.py
odoo/addons/stock_picking_reallocation/models/stock_picking_reallocation.py
odoo/addons/stock_picking_reallocation/readme/CONTRIBUTORS.rst
odoo/addons/stock_picking_reallocation/readme/DESCRIPTION.rst
odoo/addons/stock_picking_reallocation/readme/ROADMAP.rst
odoo/addons/stock_picking_reallocation/readme/USAGE.rst
odoo/addons/stock_picking_reallocation/security/ir.model.access.csv
odoo/addons/stock_picking_reallocation/static/description/icon.png
odoo/addons/stock_picking_reallocation/static/description/index.html
odoo/addons/stock_picking_reallocation/tests/__init__.py
odoo/addons/stock_picking_reallocation/tests/test_stock_picking_reallocation.py
odoo/addons/stock_picking_reallocation/views/stock_picking_reallocation_views.xml
odoo/addons/stock_picking_reallocation/views/stock_picking_views.xml
odoo14_addon_stock_picking_reallocation-14.0.1.0.1.dev6.dist-info/METADATA
odoo14_addon_stock_picking_reallocation-14.0.1.0.1.dev6.dist-info/WHEEL
odoo14_addon_stock_picking_reallocation-14.0.1.0.1.dev6.dist-info/top_level.txt
odoo14_addon_stock_picking_reallocation-14.0.1.0.1.dev6.dist-info/RECORD
